[
  {
    "line": 20,
    "elements": [
      {
        "BDD_TESTRUN_UUID": "f2960488-29ee-41ce-8581-d6c9f744b3ca",
        "line": 32,
        "name": "Validacion inicio sesion con credenciales correctas",
        "description": "",
        "id": "iniciar-sesión-en-portal-mercadeo;validacion-inicio-sesion-con-credenciales-correctas;;2",
        "type": "scenario",
        "keyword": "Scenario Outline",
        "steps": [
          {
            "result": {
              "duration": 8603004500,
              "status": "passed"
            },
            "line": 25,
            "name": "El usuario navega la pagina de inicio de sesion de mercadeo",
            "match": {
              "location": "LoginSteps.navegarPaginaInicioSesion()"
            },
            "keyword": "Given ",
            "BDD_STEP_UUID": "d6587389-20c3-41c8-8295-c5b44dbe231a"
          },
          {
            "result": {
              "duration": 1416226500,
              "status": "passed"
            },
            "line": 26,
            "name": "ingresa usuario ldpappsl3 y contrasena r1vjgeft2cxJ7NAvIwi5jQ\u003d\u003d",
            "match": {
              "arguments": [
                {
                  "val": "ldpappsl3",
                  "offset": 16
                },
                {
                  "val": "r1vjgeft2cxJ7NAvIwi5jQ\u003d\u003d",
                  "offset": 39
                }
              ],
              "location": "LoginSteps.ingresarCredenciales(String,String)"
            },
            "keyword": "When ",
            "BDD_STEP_UUID": "79e57925-83d8-491a-83da-7c35dc7e3f10"
          },
          {
            "result": {
              "duration": 777968500,
              "status": "passed"
            },
            "line": 27,
            "name": "Clic sobre el boton ingresar",
            "match": {
              "location": "LoginSteps.darClicBtnContinuar()"
            },
            "keyword": "And ",
            "BDD_STEP_UUID": "947fe025-e26d-4deb-a8f4-d963af9f5394"
          },
          {
            "result": {
              "duration": 791200,
              "status": "passed"
            },
            "line": 28,
            "name": "el sistema verifica el status",
            "match": {
              "location": "LoginSteps.verificarLogueo()"
            },
            "keyword": "Then ",
            "BDD_STEP_UUID": "76080569-24cc-41e9-8e81-654b536ed9f3"
          }
        ],
        "tags": [
          {
            "name": "@tag"
          },
          {
            "name": "@tag1"
          }
        ]
      }
    ],
    "name": "Iniciar sesión en portal mercadeo",
    "description": "  Como usuario del portal mercadeo, deseo ingresar al introducir las credenciales",
    "id": "iniciar-sesión-en-portal-mercadeo",
    "keyword": "Feature",
    "uri": "C:/Users/dimartinez/Katalon Studio/Mercadeo_BDD/Include/features/Login.feature",
    "tags": [
      {
        "name": "@tag",
        "type": "Tag",
        "location": {
          "line": 19,
          "column": 1
        }
      }
    ]
  }
]